torchtraps/__init__.py
torchtraps/coco_camera_traps_loader.py
torchtraps/config.py
torchtraps/inference.py
torchtraps/lightning.py
torchtraps/linear_evaluation_protocol.py
torchtraps/magic.py
torchtraps/models.py
torchtraps/run.py
torchtraps/self_supervised.py
torchtraps/torchtraps.py
torchtraps/train.py
torchtraps/train_detection.py
torchtraps-0.1.4.dist-info/AUTHORS.rst
torchtraps-0.1.4.dist-info/LICENSE
torchtraps-0.1.4.dist-info/METADATA
torchtraps-0.1.4.dist-info/WHEEL
torchtraps-0.1.4.dist-info/entry_points.txt
torchtraps-0.1.4.dist-info/top_level.txt
torchtraps-0.1.4.dist-info/RECORD
